mht/__init__.py
mht/constants.py
mht/scan_volume.py
mht/models/__init__.py
mht/models/measmodel.py
mht/models/motionmodel.py
mht/models/target.py
mht/tracker/__init__.py
mht/tracker/data_association.py
mht/tracker/tracker.py
mht/utils/__init__.py
mht/utils/gaussian.py
mht/utils/generation.py
mht/utils/metrics.py
mht/utils/plot.py
mht-0.0.1.dist-info/METADATA
mht-0.0.1.dist-info/WHEEL
mht-0.0.1.dist-info/top_level.txt
mht-0.0.1.dist-info/RECORD
