Metadata-Version: 2.1
Name: mht
Version: 0.0.1
Summary: Track-oriented multiple hypothesis tracker
Home-page: https://github.com/osannolik/mh-tracker
Author: osannolik
Author-email: osannolik.pypi@godtycklig.se
License: MIT
Keywords: MOT,MTT,MHT,JPDA,PMBM,tracking
Platform: UNKNOWN
Classifier: License :: OSI Approved :: MIT License
Classifier: Programming Language :: Python
Classifier: Programming Language :: Python :: 3
Requires-Dist: numpy
Requires-Dist: matplotlib
Requires-Dist: motmetrics
